chi_operator/__init__.py
chi_operator/__main__.py
chi_operator/base.py
chi_operator/cli.py
chi_operator/lease.py
chi_operator/network.py
chi_operator/node.py
chi_operator/user.py
chi_operator/util.py
python_chi_operator-0.4.3.dist-info/LICENSE
python_chi_operator-0.4.3.dist-info/METADATA
python_chi_operator-0.4.3.dist-info/WHEEL
python_chi_operator-0.4.3.dist-info/entry_points.txt
python_chi_operator-0.4.3.dist-info/top_level.txt
python_chi_operator-0.4.3.dist-info/RECORD
