Metadata-Version: 2.1
Name: python-chi-operator
Version: 0.4.3
Summary: Operator library for Chameleon
Home-page: https://www.chameleoncloud.org
Author: University of Chicago
Author-email: contact@chameleoncloud.org
License: UNKNOWN
Platform: UNKNOWN
Classifier: Development Status :: 4 - Beta
Classifier: Environment :: Console
Classifier: Environment :: OpenStack
Classifier: Intended Audience :: Science/Research
Classifier: Intended Audience :: System Administrators
Classifier: Operating System :: OS Independent
Classifier: Programming Language :: Python
Requires-Dist: click
Requires-Dist: click-spinner
Requires-Dist: crudini
Requires-Dist: python-blazarclient
Requires-Dist: python-dateutil
Requires-Dist: python-dracclient
Requires-Dist: python-ironicclient
Requires-Dist: python-neutronclient
Requires-Dist: python-chi (>=0.10.0)
Requires-Dist: PyYAML
Requires-Dist: tabulate
